platitudes/__init__.py
platitudes/actions.py
platitudes/argument.py
platitudes/errors.py
platitudes/platitudes.py
platitudes-2.0.0.dist-info/LICENSE
platitudes-2.0.0.dist-info/METADATA
platitudes-2.0.0.dist-info/WHEEL
platitudes-2.0.0.dist-info/RECORD
